CHANGELOG.rst
COPYING
COPYING.LESSER
MANIFEST.in
README.rst
alembic.ini
createdb.py
setup.py
alembic/README
alembic/env.py
alembic/script.py.mako
alembic/versions/167e0e6dd4e5_make_code_path_longer.py
alembic/versions/18ebf3181f87_add_a_negated_column_for_rules.py
alembic/versions/1b6e419ea1a6_add_threshold1_to_existing_prefs.py
alembic/versions/1be98d56336_drop_the_mention_rule_from_the_defaults.py
alembic/versions/2136a1f22f1f_cull_removed_rules.py
alembic/versions/226fd58fe7e5_ignore_taskotron_messages_in_the_main_.py
alembic/versions/24533471e302_add_the_verbose_column.py
alembic/versions/2ea9623b21fa_add_an_active_field_to_filter.py
alembic/versions/33082c0ecf3f_add_presentation_booleans.py
alembic/versions/362efe8fd524_add_new_masher_rules.py
alembic/versions/38c9c18d342e_add_new_mdapi_rule.py
alembic/versions/3de9ad66862f_cascade_removed_rules_to_filters.py
alembic/versions/4a95022fd7f3_add_another_presentation_boolean.py
alembic/versions/5403906cbd9f_add_new_taskotron_filter.py
alembic/versions/59ee93c4bf71_add_the_oneshot_column.py
fmn/__init__.py
fmn.lib.egg-info/PKG-INFO
fmn.lib.egg-info/SOURCES.txt
fmn.lib.egg-info/dependency_links.txt
fmn.lib.egg-info/namespace_packages.txt
fmn.lib.egg-info/not-zip-safe
fmn.lib.egg-info/requires.txt
fmn.lib.egg-info/top_level.txt
fmn/lib/__init__.py
fmn/lib/defaults.py
fmn/lib/hinting.py
fmn/lib/models.py