Metadata-Version: 1.1
Name: fmn.lib
Version: 0.8.2
Summary: Internal API components and model for Fedora Notifications
Home-page: https://github.com/fedora-infra/fmn.lib
Author: Ralph Bean
Author-email: rbean@redhat.com
License: LGPLv2+
Download-URL: https://pypi.python.org/pypi/fmn.lib/
Platform: UNKNOWN
Classifier: Environment :: Web Environment
Classifier: Topic :: Software Development :: Libraries :: Python Modules
Classifier: Intended Audience :: Developers
Classifier: Programming Language :: Python
